p1_f9.v
module f9(input w, x, y, z, output o);

    wire a, b, c, d;
    and a1(a, x, z);
    and a2(b, w, x, ~y);
    and a3(c, w, ~y, z);
    and a4(d, ~x, y, ~z);
    or o1(o, a, b, c, d);

endmodule

p1_tb.v
`timescale 1ps/1ps
`include "p1_f9.v"

module breadboard;
    reg W, X, Y, Z;
    wire A;

    f9 eq9(W, X, Y, Z, A);

    initial
    begin
        $dumpfile("p1.vcd");
        $dumpvars(0, breadboard);

        W = 0; X = 0; Y = 0; Z = 0; #10;
        W = 0; X = 0; Y = 0; Z = 1; #10;
        W = 0; X = 0; Y = 1; Z = 0; #10;
        W = 0; X = 0; Y = 1; Z = 1; #10;

        W = 0; X = 1; Y = 0; Z = 0; #10;
        W = 0; X = 1; Y = 0; Z = 1; #10;
        W = 0; X = 1; Y = 1; Z = 0; #10;
        W = 0; X = 1; Y = 1; Z = 1; #10;

        W = 1; X = 0; Y = 0; Z = 0; #10;
        W = 1; X = 0; Y = 0; Z = 1; #10;
        W = 1; X = 0; Y = 1; Z = 0; #10;
        W = 1; X = 0; Y = 1; Z = 1; #10;

        W = 1; X = 1; Y = 0; Z = 0; #10;
        W = 1; X = 1; Y = 0; Z = 1; #10;
        W = 1; X = 1; Y = 1; Z = 0; #10;
        W = 1; X = 1; Y = 1; Z = 1; #10;

        $finish;
    end

    initial
        $monitor("Time = %2t, W = %d, X = %d, Y = %d, Z = %d, A = %d", $time, W, X, Y, Z, A); // Prints if any variables change

endmodule

p1.vcd
$date
	Wed Feb 09 12:10:19 2022
$end
$version
	Icarus Verilog
$end
$timescale
	1ps
$end
$scope module breadboard $end
$var wire 1 ! A $end
$var reg 1 " W $end
$var reg 1 # X $end
$var reg 1 $ Y $end
$var reg 1 % Z $end
$scope module eq9 $end
$var wire 1 & a $end
$var wire 1 ' b $end
$var wire 1 ( c $end
$var wire 1 ) d $end
$var wire 1 ! o $end
$var wire 1 " w $end
$var wire 1 # x $end
$var wire 1 $ y $end
$var wire 1 % z $end
$upscope $end
$upscope $end
$enddefinitions $end
#0
$dumpvars
0)
0(
0'
0&
0%
0$
0#
0"
0!
$end
#10
1%
#20
1!
1)
0%
1$
#30
0!
0)
1%
#40
0%
0$
1#
#50
1!
1&
1%
#60
0!
0&
0%
1$
#70
1!
1&
1%
#80
0!
0&
0%
0$
0#
1"
#90
1!
1(
1%
#100
1)
0(
0%
1$
#110
0!
0)
1%
#120
1!
1'
0%
0$
1#
#130
1&
1(
1%
#140
0!
0'
0&
0(
0%
1$
#150
1!
1&
1%
